{ 
"firstName": "Людвиг", 
"lastName": "Иванович", 
"middleName": "Сидоров", 
"birthDate": "01.01.2018", 
"birthPlace": "Свердловская обл. г. Екатеринбург", 
"sex": 1, 
"contacts": { 
"address": "Екатеринбург, ул. Гоголя, д. 36, оф. 900", 
"mobilePhone": "+79711111741", 
"email": "inf10666661@atlas.com" 
}, 
"events": { 
"isSMS": true, 
"isEMail": false 
}, 
"docs": { 
"passport": { 
"num": "1234123990", 
"date": "08.07.2016", 
"codeOrg": "660123", 
"org": "ОТДЕЛЕНИЕМ УФМС РОССИИ ПО СВЕРДЛОВСКОЙ ОБЛАСТИ ГОР. ЕКАТЕРИНБУРГ", 
"addressReg": "г. Екатеринбург, ул. Учителей, д. 15" 
}, 
"snils": "16793747330" 
} 
} 